pymongo_automation/__init__.py
pymongo_automation/mongo_crud.py
pymongo_automation-0.0.2.dist-info/LICENSE
pymongo_automation-0.0.2.dist-info/METADATA
pymongo_automation-0.0.2.dist-info/WHEEL
pymongo_automation-0.0.2.dist-info/top_level.txt
pymongo_automation-0.0.2.dist-info/RECORD
