Metadata-Version: 2.1
Name: pymongo-automation
Version: 0.0.2
Summary: A python package for connecting with database.
Home-page: https://github.com/chaitanya-24/mongodb_connector_package_
Author: chaitanya-24
Author-email: csawant2407@gmail.com
License: MIT
Project-URL: Bug Tracker, https://github.com/chaitanya-24/mongodb_connector_package_/issues
Classifier: Programming Language :: Python :: 3
Classifier: License :: OSI Approved :: MIT License
Requires-Python: >=3.7
License-File: LICENSE
Requires-Dist: pymongo
Requires-Dist: pymongo[srv]
Requires-Dist: dnspython
Requires-Dist: pandas
Requires-Dist: numpy
Requires-Dist: ensure
Requires-Dist: pytest
Provides-Extra: testing
Requires-Dist: pytest>=7.1.3; extra == "testing"
Requires-Dist: mypy>=0.971; extra == "testing"
Requires-Dist: flake8>=5.0.4; extra == "testing"
Requires-Dist: tox>=3.25.1; extra == "testing"
Requires-Dist: black>=22.8.0; extra == "testing"
